_version.py
foo2bar/__init__.py
foo2bar/cli.py
foo2bar/evallib.py
foo2bar/logging.py
foo2bar/matchers.py
foo2bar/node_converter.py
foo2bar/providers.py
foo2bar/transformers.py
foo2bar/wrapper.py
foo2bar-0.0.2.dist-info/METADATA
foo2bar-0.0.2.dist-info/WHEEL
foo2bar-0.0.2.dist-info/entry_points.txt
foo2bar-0.0.2.dist-info/top_level.txt
foo2bar-0.0.2.dist-info/RECORD
