Metadata-Version: 2.2
Name: foo2bar
Version: 0.0.2
Summary: A python library for substituting values in a script.
Author-email: Martin Favin-Lévêque <martin.fl97@gmail.com>
Keywords: substitute,replace,values,parameter,script,configuration,automation,templating,dynamic,injection
Classifier: Operating System :: OS Independent
Classifier: Development Status :: 3 - Alpha
Classifier: License :: OSI Approved :: MIT License
Requires-Python: >=3.11
Requires-Dist: libcst==1.5.0
Requires-Dist: RestrictedPython==7.4
